w3av/__init__.py
w3av/config/file_extensions.txt
w3av/config/iana_mimetypes.txt
w3av/config/mimetypes.txt
w3av/config/nodetypes.txt
w3av/core/__init__.py
w3av/core/argparser.py
w3av/core/comment.py
w3av/core/context.py
w3av/core/html.py
w3av/core/jsparser.py
w3av/core/output.py
w3av/core/url_utils.py
w3av/modes/__init__.py
w3av/modes/inspect.py
w3av/modes/query.py
w3av/modes/strings.py
w3av/modes/tree.py
w3av/modes/urls/__init__.py
w3av/modes/urls/aliases.py
w3av/modes/urls/config.py
w3av/modes/urls/extractor.py
w3av/modes/urls/filters.py
w3av/modes/urls/output.py
w3av/modes/urls/processors.py
w3av/modes/urls/resolvers.py
w3av/modes/urls/symbols.py
w3av/modes/urls/traversal.py
w3av/w3av.py
w3av-1.0.6.dist-info/LICENSE.md
w3av-1.0.6.dist-info/METADATA
w3av-1.0.6.dist-info/WHEEL
w3av-1.0.6.dist-info/entry_points.txt
w3av-1.0.6.dist-info/RECORD
