Metadata-Version: 2.1
Name: w3av
Version: 1.0.6
Summary: extract URLs, strings, and more from JavaScript code
License: MIT
Author: Shuaib Oladigbolu
Author-email: shuaib@footstep.ninja
Requires-Python: >=3.11,<4.0
Classifier: License :: OSI Approved :: MIT License
Classifier: Programming Language :: Python :: 3
Classifier: Programming Language :: Python :: 3.11
Classifier: Programming Language :: Python :: 3.12
Requires-Dist: argcomplete (>=3.2.0,<4.0.0)
Requires-Dist: beautifulsoup4 (>=4.14.3,<5.0.0)
Requires-Dist: html5-parser (>=0.4.12,<0.5.0)
Requires-Dist: html5lib (>=1.1,<2.0)
Requires-Dist: lxml (>=5.3.0,<6.0.0)
Requires-Dist: tree-sitter (>=0.25.2,<0.26.0)
Requires-Dist: tree-sitter-javascript (>=0.25.0,<0.26.0)
